sqlitehandler/__init__.py
sqlitehandler/sqlitehandler.py
src/__init__.py
src/sqlitehandler.py
sqlitehandler-0.1.0.dist-info/LICENSE
sqlitehandler-0.1.0.dist-info/METADATA
sqlitehandler-0.1.0.dist-info/WHEEL
sqlitehandler-0.1.0.dist-info/top_level.txt
sqlitehandler-0.1.0.dist-info/RECORD
