Metadata-Version: 2.1
Name: sqlitehandler
Version: 0.1.0
Summary: SQLite handler package
Home-page: https://github.com/Danelfcf/SQLiteHandler/tree/main
Author: daniel F.C.F. 
Project-URL: Bug Tracker, https://github.com/Danelfcf/SQLiteHandler/issues
Classifier: Development Status :: 1 - Planning
Classifier: Intended Audience :: Developers
Classifier: Programming Language :: Python :: 3
Classifier: License :: OSI Approved :: MIT License
Classifier: Operating System :: OS Independent
License-File: LICENSE
